ariadne_graphql_modules/__init__.py
ariadne_graphql_modules/bases.py
ariadne_graphql_modules/collection_type.py
ariadne_graphql_modules/convert_case.py
ariadne_graphql_modules/dependencies.py
ariadne_graphql_modules/directive_type.py
ariadne_graphql_modules/enum_type.py
ariadne_graphql_modules/executable_schema.py
ariadne_graphql_modules/input_type.py
ariadne_graphql_modules/interface_type.py
ariadne_graphql_modules/mutation_type.py
ariadne_graphql_modules/object_type.py
ariadne_graphql_modules/py.typed
ariadne_graphql_modules/resolvers_mixin.py
ariadne_graphql_modules/scalar_type.py
ariadne_graphql_modules/subscription_type.py
ariadne_graphql_modules/types.py
ariadne_graphql_modules/union_type.py
ariadne_graphql_modules/utils.py
ariadne_graphql_modules-0.8.0.dist-info/METADATA
ariadne_graphql_modules-0.8.0.dist-info/WHEEL
ariadne_graphql_modules-0.8.0.dist-info/licenses/LICENSE
ariadne_graphql_modules-0.8.0.dist-info/RECORD
