Metadata-Version: 2.1
Name: ariadne-graphql-modules
Version: 0.8.0
Summary: Ariadne toolkit for defining GraphQL schemas in modular fashion.
Project-URL: Homepage, https://ariadnegraphql.org/
Project-URL: Repository, https://github.com/mirumee/ariadne-graphql-modules
Project-URL: Bug Tracker, https://github.com/mirumee/ariadne-graphql-modules/issues
Project-URL: Community, https://github.com/mirumee/ariadne/discussions
Project-URL: Twitter, https://twitter.com/AriadneGraphQL
Author-email: Mirumee Software <hello@mirumee.com>
License: BSD 3-Clause License
License-File: LICENSE
Classifier: Development Status :: 4 - Beta
Classifier: Intended Audience :: Developers
Classifier: License :: OSI Approved :: BSD License
Classifier: Operating System :: OS Independent
Classifier: Programming Language :: Python
Classifier: Programming Language :: Python :: 3.8
Classifier: Programming Language :: Python :: 3.9
Classifier: Programming Language :: Python :: 3.10
Classifier: Programming Language :: Python :: 3.11
Classifier: Topic :: Software Development :: Libraries :: Python Modules
Requires-Dist: ariadne>=0.22.0
Provides-Extra: test
Requires-Dist: black; extra == 'test'
Requires-Dist: mypy; extra == 'test'
Requires-Dist: pylint; extra == 'test'
Requires-Dist: pytest; extra == 'test'
Requires-Dist: pytest-asyncio; extra == 'test'
Requires-Dist: snapshottest; extra == 'test'
